bamboo_stash/__init__.py
bamboo_stash/stash.py
bamboo_stash-0.1.3.dist-info/METADATA
bamboo_stash-0.1.3.dist-info/WHEEL
bamboo_stash-0.1.3.dist-info/RECORD
