Metadata-Version: 2.3
Name: bamboo-stash
Version: 0.1.3
Summary: Automatic caching for Pandas function pipelines.
Project-URL: Documentation, https://bamboo-stash.readthedocs.io
Project-URL: Repository, https://github.com/dhrosa/bamboo-stash
Author-email: Diony Rosa <dhrosa+dev@gmail.com>
License-Expression: MIT
Keywords: pandas
Requires-Python: >=3.10
Requires-Dist: pandas
Requires-Dist: platformdirs
